teststand_tamer-0.0.1.dist-info/METADATA
teststand_tamer-0.0.1.dist-info/WHEEL
teststand_tamer/__init__.py
teststand_tamer-0.0.1.dist-info/RECORD
